dsites/__init__.py
dsites/collectf_export.tsv
dsites/main.py
dsites/predictor.py
dsites-1.1.1.dist-info/licenses/LICENSE
dsites-1.1.1.dist-info/METADATA
dsites-1.1.1.dist-info/WHEEL
dsites-1.1.1.dist-info/entry_points.txt
dsites-1.1.1.dist-info/top_level.txt
dsites-1.1.1.dist-info/RECORD
