Metadata-Version: 2.4
Name: dsites
Version: 1.1.1
Summary: D-Sites: Hybrid TFBS predictor (PWM + DNA shape + RF)
Home-page: https://github.com/pankaj357/D-Sites
Author: Pankaj, Kanaka KK
Author-email: ft.pank@gmail.com
Classifier: Development Status :: 5 - Production/Stable
Classifier: Intended Audience :: Science/Research
Classifier: Topic :: Scientific/Engineering :: Bio-Informatics
Classifier: License :: OSI Approved :: MIT License
Classifier: Programming Language :: Python :: 3
Classifier: Programming Language :: Python :: 3.13
Requires-Python: >=3.10
License-File: LICENSE
Requires-Dist: biopython>=1.79
Requires-Dist: pandas>=1.3
Requires-Dist: numpy>=1.21
Requires-Dist: scikit-learn>=1.0
Requires-Dist: matplotlib>=3.3
Requires-Dist: tqdm>=4.62
Dynamic: author
Dynamic: author-email
Dynamic: classifier
Dynamic: description
Dynamic: description-content-type
Dynamic: home-page
Dynamic: license-file
Dynamic: requires-dist
Dynamic: requires-python
Dynamic: summary
